PointQuality/__init__.py
PointQuality/gta_quality_metrics.py
PointQuality/quality_metrics.py
PointQuality-0.1.2.dist-info/METADATA
PointQuality-0.1.2.dist-info/WHEEL
PointQuality-0.1.2.dist-info/top_level.txt
PointQuality-0.1.2.dist-info/RECORD
