Metadata-Version: 2.1
Name: PointQuality
Version: 0.1.2
Summary: Compute local and global quality metrics for comparing point clouds
Home-page: https://github.com/DavidFernandezBonet/PointQuality
Author: David Fernandez Bonet
Author-email: davferdz@gmail.com
Classifier: Programming Language :: Python :: 3
Classifier: License :: OSI Approved :: MIT License
Classifier: Operating System :: OS Independent
Requires-Python: >=3.6
Requires-Dist: numpy
Requires-Dist: scipy
Requires-Dist: pandas
Requires-Dist: matplotlib
Requires-Dist: networkx
Requires-Dist: python-igraph
